file_search_tk/__init__.py
file_search_tk/app.py
file_search_tk/nul_test.txt
file_search_tk-0.1.7.dist-info/LICENSE
file_search_tk-0.1.7.dist-info/METADATA
file_search_tk-0.1.7.dist-info/WHEEL
file_search_tk-0.1.7.dist-info/entry_points.txt
file_search_tk-0.1.7.dist-info/RECORD
