Metadata-Version: 2.3
Name: file-search-tk
Version: 0.1.7
Summary: A tkinter app to search files based on a pattern
License: MIT
Author: Mateo Velez
Author-email: mateo.velezcobian@gmail.com
Requires-Python: >=3.9
Classifier: License :: OSI Approved :: MIT License
Classifier: Programming Language :: Python :: 3
Classifier: Programming Language :: Python :: 3.9
Classifier: Programming Language :: Python :: 3.10
Classifier: Programming Language :: Python :: 3.11
Classifier: Programming Language :: Python :: 3.12
Classifier: Programming Language :: Python :: 3.13
